odoo/addons/stock_scrap_location_default/README.rst
odoo/addons/stock_scrap_location_default/__init__.py
odoo/addons/stock_scrap_location_default/__manifest__.py
odoo/addons/stock_scrap_location_default/i18n/it.po
odoo/addons/stock_scrap_location_default/i18n/stock_scrap_location_default.pot
odoo/addons/stock_scrap_location_default/models/__init__.py
odoo/addons/stock_scrap_location_default/models/res_company.py
odoo/addons/stock_scrap_location_default/models/res_config_settings.py
odoo/addons/stock_scrap_location_default/models/stock_scrap.py
odoo/addons/stock_scrap_location_default/readme/CONFIGURE.rst
odoo/addons/stock_scrap_location_default/readme/CONTRIBUTORS.rst
odoo/addons/stock_scrap_location_default/readme/DESCRIPTION.rst
odoo/addons/stock_scrap_location_default/readme/ROADMAP.rst
odoo/addons/stock_scrap_location_default/static/description/icon.png
odoo/addons/stock_scrap_location_default/static/description/index.html
odoo/addons/stock_scrap_location_default/tests/__init__.py
odoo/addons/stock_scrap_location_default/tests/test_scrap_location_default.py
odoo/addons/stock_scrap_location_default/views/res_config_settings.xml
odoo_addon_stock_scrap_location_default-16.0.1.0.0.4.dist-info/METADATA
odoo_addon_stock_scrap_location_default-16.0.1.0.0.4.dist-info/WHEEL
odoo_addon_stock_scrap_location_default-16.0.1.0.0.4.dist-info/top_level.txt
odoo_addon_stock_scrap_location_default-16.0.1.0.0.4.dist-info/RECORD
